boarml/__init__.py
boarml/architectures/__init__.py
boarml/architectures/cnn_architecture.py
boarml/builders/__init__.py
boarml/builders/base_builder.py
boarml/builders/keras_builder.py
boarml/cnn/__init__.py
boarml/cnn/layers.py
boarml/cnn/model.py
boarml/cnn/unit.py
boarml/generators/__init__.py
boarml/generators/model_generator.py
boarml-0.0.6.dist-info/LICENSE
boarml-0.0.6.dist-info/METADATA
boarml-0.0.6.dist-info/WHEEL
boarml-0.0.6.dist-info/top_level.txt
boarml-0.0.6.dist-info/RECORD
