Metadata-Version: 2.1
Name: boarml
Version: 0.0.6
Summary: Package for building abstract ML models that can then be compiled using popular ML platforms.
Home-page: https://github.com/DobromirM/BoarML
Author: Dobromir Marinov
Author-email: mr.d.marinov@gmail.com
License: UNKNOWN
Platform: UNKNOWN
Classifier: Programming Language :: Python :: 3
Classifier: License :: OSI Approved :: GNU General Public License (GPL)
Classifier: Operating System :: OS Independent
